{
  "id": "64839429",
  "source": "testrail",
  "type": "testcase",
  "project": "411453",
  "title": "[IOS] Location Sharing Dialogue - Don't Allow - Enable Now - Allow While Using App",
  "feature": "App Settings",
  "scenario": "Find My Device screen fails to update after granting location permission via \"Enable Now\" when \"Don't Allow\" was selected during onboarding",
  "steps": [
    "1. Launch the Poly Studio Mobile app and complete the onboarding flow, selecting \"Don't Allow\" when prompted for location permission.",
    "2. Navigate to App Settings \u2192 Find My Device.",
    "3. Tap \"Enable Now\" on the Find My Device screen.",
    "4. When the system location permission dialog appears, select \"While Using the App\".",
    "5. Return to the Poly Studio Mobile app."
  ],
  "expected": "The location permission dialog is dismissed and the Find My Device screen is displayed.",
  "coverage": [],
  "edge_cases": [],
  "keywords": [
    "find-my-device",
    "location-permission",
    "enable-now",
    "poly-studio-mobile",
    "onboarding",
    "app-settings",
    "permission-granting",
    "ui-update-failure"
  ],
  "source_last_updated": "1759150486",
  "source_hash": "70dd6e57d57b180a7975da950ca006e1daf01a559f527302ca9f0f25341f53ec",
  "context_version": "v1",
  "processed_at": "2026-04-25T08:21:30.912375Z",
  "status": "active"
}