{
  "id": "64839423",
  "source": "testrail",
  "type": "testcase",
  "project": "411453",
  "title": "[IOS] Location sharing dialogue is visible on the Home Screen",
  "feature": "App Settings",
  "scenario": "Location sharing permission dialog appears on Home Screen after first-time app launch and license acceptance in Poly Lens app",
  "steps": [
    "Launch the Poly Studio Mobile app for the first time",
    "Accept the license agreement and privacy policy",
    "Tap Continue",
    "Tap Skip or Continue as Guest / Login",
    "Observe the Home screen"
  ],
  "expected": "The user lands on the Home screen without any location sharing dialogue.",
  "coverage": [],
  "edge_cases": [],
  "keywords": [
    "poly-lens-app",
    "poly-studio-mobile",
    "first-time-launch",
    "location-permission",
    "home-screen",
    "license-acceptance",
    "app-onboarding",
    "privacy-policy"
  ],
  "source_last_updated": "1759149897",
  "source_hash": "e1e5aed335f52b0d6a720088bef740cd9a1f5df5471fdd19e4479f6f39ac4fe7",
  "context_version": "v1",
  "processed_at": "2026-04-25T09:32:26.133665Z",
  "status": "active"
}