{
  "id": "64907050",
  "source": "testrail",
  "type": "testcase",
  "project": "411453",
  "title": "App Settings - General - Account - Invite sent, user logs during the installation, not registered on Cloud",
  "feature": "App Settings",
  "scenario": "IT admin invite persists in Poly Studio Mobile app Account screen for unregistered mobile user who never accepted invite via external source",
  "steps": [
    "1. Install Poly Studio Mobile app on an Android device.",
    "2. During onboarding, log in with the mobile user account that was invited by an IT admin to a tenant.",
    "3. Complete the onboarding flow.",
    "4. Navigate to the Home screen.",
    "5. Tap the Account icon or navigate to General \u2192 Account.",
    "6. Observe the account card details.",
    "7. Check whether Tenant ID and Tenant Name rows are displayed on the account card.",
    "8. Verify the cloud registration status of the mobile user.",
    "9. Check if the invite to the tenant is still shown in the app."
  ],
  "expected": "The mobile user should be fully registered on the cloud with Tenant ID and Tenant Name rows present on the account card. The invite to the tenant should not be shown after login, or should be properly handled based on the user's registration status.",
  "coverage": [],
  "edge_cases": [],
  "keywords": [
    "poly-studio-mobile",
    "it-admin-invite",
    "tenant-registration",
    "account-screen",
    "cloud-registration-status",
    "mobile-user-onboarding",
    "unregistered-user",
    "tenant-id"
  ],
  "source_last_updated": "1759416375",
  "source_hash": "22db7ea724dad989b29d4b2ce4e05000538c076eefd6b853ebde20c8ec71c2bf",
  "context_version": "v1",
  "processed_at": "2026-04-25T08:21:30.933803Z",
  "status": "active"
}