{
  "id": "65293025",
  "source": "testrail",
  "type": "testcase",
  "project": "411453",
  "title": "Onboarding - Eula page - License Agreement and Privacy Policy links when the internet is turned off",
  "feature": "Onboarding - EULA Page",
  "scenario": "User taps License Agreement or Privacy Policy links on EULA page without internet and sees \"Something went wrong\" screen, then returns to \"Well hello, first things first...\" screen after tapping Cancel",
  "steps": [
    "Turn off internet connection on the device.",
    "Open the app and navigate to the EULA page.",
    "Tap the License Agreement link.",
    "Observe the screen displayed.",
    "Tap the Cancel button.",
    "Observe the resulting screen."
  ],
  "expected": "Tapping the License Agreement or Privacy Policy links should display the respective agreement content.",
  "coverage": [],
  "edge_cases": [],
  "keywords": [
    "EULA",
    "License Agreement",
    "Privacy Policy",
    "offline",
    "no internet",
    "error screen",
    "Cancel button",
    "app navigation"
  ],
  "source_last_updated": "1760528315",
  "source_hash": "0eb2aa1ed38ea63c0fb8a78c84604e51fdcd7d6fcea6253bae5fc7e7f9352691",
  "context_version": "v1",
  "processed_at": "2026-04-24T10:51:32.703985Z",
  "status": "active"
}