{
  "id": "65459441",
  "source": "testrail",
  "type": "testcase",
  "project": "411453",
  "title": "Software Update - DFU - Charge Case at low battery - Software update tab in device settings",
  "feature": "Firmware Update",
  "scenario": "DFU blocked with low battery popup when charge case battery is below 5% and not plugged into power",
  "steps": [
    "Open Poly Studio Mobile app",
    "Navigate to Home screen",
    "Tap on the connected device name to open Device Settings",
    "Scroll to and tap 'Firmware Update' or 'DFU' option",
    "Observe the app response when attempting to start the update",
    "Ensure the charge case battery is below 5% (not plugged in)",
    "Attempt to start the firmware update",
    "Observe the popup message displayed",
    "Plug the charge case into power",
    "Attempt the firmware update again",
    "While the update is in progress, unplug the charge case from power (battery still below 5%)",
    "Observe the app behavior after unplugging"
  ],
  "expected": "When the charge case battery is below 5% and not plugged in, the app shows a popup: 'Update currently not available, please try back later'. The update proceeds only after the charge case is plugged into power. If the device is unplugged during the update while battery is still below 5%, the popup reappears and blocks the update.",
  "coverage": [],
  "edge_cases": [],
  "keywords": [
    "dfu-blocked",
    "low-battery-popup",
    "charge-case-battery",
    "firmware-update",
    "poly-studio-mobile",
    "battery-persistence",
    "power-interruption",
    "device-settings"
  ],
  "source_last_updated": "1763369632",
  "source_hash": "2fa50f275a2b8df92cf5bafd12c8b567932e35e17eca3c654393c5a472307dcc",
  "context_version": "v1",
  "processed_at": "2026-04-25T09:32:26.290119Z",
  "status": "active"
}