{
  "id": "65641568",
  "source": "testrail",
  "type": "testcase",
  "project": "411453",
  "title": "EQ - Reset EQ and Save EQ becomes active only after moving slider",
  "feature": "Equalizer",
  "scenario": "Reset EQ and Save EQ buttons remain disabled until a slider is adjusted in Custom EQ settings",
  "steps": [
    "Open Poly Studio Mobile app",
    "Navigate to Home screen",
    "Tap on the connected device name to open Device Settings",
    "Select Audio Settings",
    "Tap on Equalizer",
    "Select the Custom EQ preset",
    "Observe the Reset EQ and Save EQ buttons",
    "Without moving any slider, check if Reset EQ and Save EQ buttons are enabled or disabled",
    "Move any slider in the Custom EQ settings",
    "Observe the Reset EQ and Save EQ buttons again"
  ],
  "expected": "Reset EQ and Save EQ buttons should be disabled (greyed out) when no slider adjustment has been made, and become enabled/active only after the user moves any slider in the Custom EQ settings.",
  "coverage": [],
  "edge_cases": [],
  "keywords": [
    "custom-eq",
    "reset-eq",
    "save-eq",
    "equalizer-settings",
    "poly-studio-mobile",
    "audio-settings",
    "eq-slider",
    "device-settings"
  ],
  "source_last_updated": "1761143529",
  "source_hash": "35c0881bc14ca3afc3f26ea9e183d54061b83ae147e4f2e9f24e0007e7a87e16",
  "context_version": "v1",
  "processed_at": "2026-04-25T09:32:26.251883Z",
  "status": "active"
}