{
  "id": "65640173",
  "source": "testrail",
  "type": "testcase",
  "project": "411453",
  "title": "Analytics - Firmware Update Completed",
  "feature": "Firmware Updates",
  "scenario": "DFU completion event count does not update immediately on Firebase dashboard after firmware update on Poly device",
  "steps": [],
  "expected": "",
  "coverage": [],
  "edge_cases": [],
  "keywords": [
    "firmware-update",
    "dfu-completion-event",
    "firebase-dashboard",
    "event-count",
    "poly-device",
    "telemetry",
    "analytics-reporting"
  ],
  "source_last_updated": "1760949700",
  "source_hash": "c82cec22de20324500f2e8f4cd30e54cacd651d401b991982ff3e376dd49fa64",
  "context_version": "v1",
  "processed_at": "2026-04-25T05:37:16.970831Z",
  "status": "active"
}