{
  "id": "65640197",
  "source": "testrail",
  "type": "testcase",
  "project": "411453",
  "title": "Soak Test - Headset disconnected, app in the foreground, phone idle",
  "feature": "App Settings",
  "scenario": "App remains responsive and does not crash after prolonged idle soak test with headset disconnected on Home Screen",
  "steps": [],
  "expected": "",
  "coverage": [],
  "edge_cases": [],
  "keywords": [
    "idle-soak-test",
    "app-responsiveness",
    "home-screen",
    "headset-disconnected",
    "crash-recovery",
    "prolonged-idle",
    "poly-app"
  ],
  "source_last_updated": "1760949727",
  "source_hash": "b21c49867cbaf439368b4916c68a52843aca3a12e79f4b2c4010e4368c59c91b",
  "context_version": "v1",
  "processed_at": "2026-04-25T08:21:31.074634Z",
  "status": "active"
}