{
  "id": "65640165",
  "source": "testrail",
  "type": "testcase",
  "project": "411453",
  "title": "Analytics - Events are not gathered if user is logged out and has not opted into data-sharing",
  "feature": "App Settings",
  "scenario": "Firebase analytics events are still gathered when user is logged out and has not opted into data-sharing",
  "steps": [
    "1. Launch the Poly Studio Mobile app while logged out of a Poly account.",
    "2. Ensure data-sharing / analytics opt-in has NOT been accepted.",
    "3. Trigger a Firebase analytics event, for example by adding a new Poly Bluetooth audio device (which fires the device_added event containing the device's serial number).",
    "4. Navigate to the Firebase console and check the event count for the device's serial number."
  ],
  "expected": "The event count for the device's serial number should NOT increase \u2014 no analytics events should be gathered when the user is logged out and has not opted into data-sharing.",
  "coverage": [],
  "edge_cases": [],
  "keywords": [
    "firebase-analytics",
    "data-sharing-opt-in",
    "poly-studio-mobile",
    "device-added-event",
    "privacy-compliance",
    "analytics-consent",
    "bluetooth-pairing",
    "serial-number"
  ],
  "source_last_updated": "1760949700",
  "source_hash": "30ba6b8f2fee002cd1d8777870bcb6c661b10588a435e42418a3913239cad78d",
  "context_version": "v1",
  "processed_at": "2026-04-25T07:55:31.989464Z",
  "status": "active"
}