{
  "id": "65810684",
  "source": "testrail",
  "type": "testcase",
  "project": "411453",
  "title": "Charge case inside screen/forth screen, left zoom in/out",
  "feature": "App Settings",
  "scenario": "Zoom toggle on charge case inside screen in QSG when tapping left circle button on fourth screen",
  "steps": [
    "Open the Poly Studio Mobile app.",
    "Navigate to the Home screen.",
    "Tap on the Quick Start Guide (QSG) option.",
    "Swipe to the fourth screen showing the charge case inside view.",
    "Tap the left circle button on the screen.",
    "Observe the zoom-in effect and new text appearing.",
    "Tap the same left circle button again."
  ],
  "expected": "Tapping the left circle button zooms in with new text appearing. Tapping it again zooms out to the original screen showing the charge case inside.",
  "coverage": [],
  "edge_cases": [],
  "keywords": [
    "poly-studio-mobile",
    "quick-start-guide",
    "qsg",
    "charge-case-inside-screen",
    "left-circle-button",
    "zoom-toggle",
    "zoom-in-effect",
    "fourth-screen"
  ],
  "source_last_updated": "1761315357",
  "source_hash": "e326035733a5a7b83a8639362a4525fbdda738fef3b1f3ffe2dd39ca9fecb45f",
  "context_version": "v1",
  "processed_at": "2026-04-25T05:37:16.854018Z",
  "status": "active"
}