{
  "id": "65868094",
  "source": "testrail",
  "type": "testcase",
  "project": "411453",
  "title": "Device Home Screen - Multiple devices - Deleting devices",
  "feature": "Device Home Screen",
  "scenario": "Verify that deleting a device from the device list works correctly when multiple devices are paired and connected, and that remaining devices are still displayed with proper connected/disconnected states.",
  "steps": [
    "Pair and connect at least 3 devices.",
    "Start the app.",
    "Turn off 2 devices.",
    "Delete one device from the device list.",
    "Verify the deleted device is properly removed from the list.",
    "Verify remaining devices are still present and properly displayed with connected/disconnected state.",
    "Turn off and delete the remaining devices.",
    "Verify all devices can be properly removed from the list."
  ],
  "expected": "The device is properly removed from the list. Remaining devices are still present and properly displayed with connected/disconnected state. All devices can be properly removed from the list.",
  "coverage": [],
  "edge_cases": [],
  "keywords": [
    "device deletion",
    "device list",
    "paired devices",
    "connected devices",
    "disconnected devices",
    "multi-device management",
    "device removal verification"
  ],
  "source_last_updated": "1762178343",
  "source_hash": "eb5958e7130069b7217f1493235b79a22c603434e7cae8553ad5b048040b4d37",
  "context_version": "v1",
  "processed_at": "2026-04-24T10:51:32.742514Z",
  "status": "active"
}