{
  "id": "65871614",
  "source": "testrail",
  "type": "testcase",
  "project": "411453",
  "title": "Device Home Screen - No device connected - Select Device link",
  "feature": "Device Management",
  "scenario": "Poly Studio Mobile app home screen \"Other devices\" button opens Poly support web page when no device is connected",
  "steps": [
    "Launch Poly Studio Mobile app",
    "Observe the Home screen when no device is connected",
    "Tap the 'Select Device' link",
    "Observe the list of supported Poly devices with images",
    "Scroll to the bottom of the list",
    "Tap the 'Other devices' button"
  ],
  "expected": "The Poly support web page opens in a browser.",
  "coverage": [],
  "edge_cases": [],
  "keywords": [
    "poly-studio-mobile",
    "other-devices",
    "select-device",
    "poly-support",
    "home-screen",
    "no-device-connected",
    "device-list"
  ],
  "source_last_updated": "1774958838",
  "source_hash": "9f4e7748d9cd731530d28706109ee05f8f4558126860e641ea893979a8283061",
  "context_version": "v1",
  "processed_at": "2026-04-25T08:21:30.912375Z",
  "status": "active"
}