{
  "id": "66317753",
  "source": "testrail",
  "type": "testcase",
  "project": "411453",
  "title": "Language Change",
  "feature": "Firmware Update",
  "scenario": "Language change for voice prompts requires firmware update via DFU process in Device Settings",
  "steps": [],
  "expected": "",
  "coverage": [],
  "edge_cases": [],
  "keywords": [
    "firmware-update",
    "dfu-process",
    "device-settings",
    "voice-prompts",
    "language-change",
    "poly-bluetooth"
  ],
  "source_last_updated": "1762244218",
  "source_hash": "0d1e2685e2fe0d37ef7519d21974a1297a6b378c5a31c1fcec0a0940ffa9e10d",
  "context_version": "v1",
  "processed_at": "2026-04-25T09:32:26.227935Z",
  "status": "active"
}