{
  "id": "66363586",
  "source": "testrail",
  "type": "testcase",
  "project": "411453",
  "title": "DFU - Three Easy Steps page - Disconnecting/Connecting earbuds to check DFU pop up",
  "feature": "Firmware Updates",
  "scenario": "DFU \"Three Easy Steps\" page shows persistent popup when one earbud is disconnected and \"Start Update\" is tapped, then returns to Three Easy Steps after dismissing popup",
  "steps": [
    "Open Poly Studio Mobile app",
    "Navigate to Home screen",
    "Connect a pair of Bluetooth earbuds (e.g., Poly Voyager Free 20)",
    "Go to Device Settings \u2192 [Device Name] \u2192 Firmware Update",
    "Wait for the 'Three Easy Steps' page to appear",
    "Disconnect one earbud (e.g., place the right earbud in the charge case)",
    "Tap 'Start Update' button",
    "Observe the popup that appears",
    "Reconnect the earbud (remove it from the charge case)",
    "Observe the popup remains visible",
    "Tap 'OK' on the popup",
    "Observe the screen returns to the 'Three Easy Steps' page",
    "Repeat steps 6\u201312 for the left earbud disconnection scenario"
  ],
  "expected": "A popup appears: 'Update currently not available, please try back later'. Reconnecting the earbud keeps the popup visible. Tapping OK closes the popup and returns the user to the 'Three Easy Steps' page. This behavior is consistent for both right and left earbud disconnection.",
  "coverage": [],
  "edge_cases": [],
  "keywords": [
    "dfu-three-easy-steps",
    "firmware-update",
    "earbud-disconnection",
    "persistent-popup",
    "poly-studio-mobile",
    "voyager-free-20",
    "start-update-button",
    "device-settings"
  ],
  "source_last_updated": "1762331664",
  "source_hash": "aa2e575fb39bd8169c4b5535149bf22971a50cdeb5e73abc789257753cb3a48a",
  "context_version": "v1",
  "processed_at": "2026-04-25T07:55:32.587850Z",
  "status": "active"
}