{
  "id": "66363551",
  "source": "testrail",
  "type": "testcase",
  "project": "411453",
  "title": "EB on the latest, CC has update - no update buttons",
  "feature": "Firmware Updates",
  "scenario": "Firmware update dialog appears on pairing and app restarts but no update buttons visible on Home or Settings screens when Companion App has update available but Earbud is already on latest version",
  "steps": [],
  "expected": "",
  "coverage": [],
  "edge_cases": [],
  "keywords": [
    "firmware-update",
    "companion-app",
    "pairing-dialog",
    "app-restart",
    "home-screen",
    "settings-screen",
    "update-button-visibility",
    "earbud-version"
  ],
  "source_last_updated": "1762331320",
  "source_hash": "99f2a0446718e770c4dc5937f55b31225dc0407e41c74e40d013401b395155b3",
  "context_version": "v1",
  "processed_at": "2026-04-25T09:32:26.340947Z",
  "status": "active"
}