{
  "id": "66363583",
  "source": "testrail",
  "type": "testcase",
  "project": "411453",
  "title": "Language Change - Disconnecting/Connecting earbuds to check DFU pop up",
  "feature": "Firmware Updates",
  "scenario": "Language update pop-up \"Update currently not available\" persists after reconnecting disconnected earbud on Voyager Free 60+",
  "steps": [
    "1. Open Poly Studio Mobile app on the Android device.",
    "2. Navigate to Home screen and tap on the connected device name to open Device Settings.",
    "3. In Device Settings, tap on 'Language' option.",
    "4. On the Language screen, select a different language from the list.",
    "5. Tap 'Update Now' button to apply the language change.",
    "6. While the update is in progress, place one earbud (e.g., right earbud) into the charging case so it disconnects.",
    "7. Observe the pop-up that appears on the screen.",
    "8. Reconnect the disconnected earbud by removing it from the charging case.",
    "9. Check if the pop-up dismisses automatically after reconnection.",
    "10. Tap 'Ok' on the pop-up to dismiss it.",
    "11. Repeat steps 1-10 with the other earbud (e.g., left earbud) disconnected instead."
  ],
  "expected": "After reconnecting the earbud, the pop-up should dismiss automatically, or the language update should complete without interruption when both earbuds are connected.",
  "coverage": [],
  "edge_cases": [],
  "keywords": [
    "voyager-free-60-plus",
    "language-update",
    "poly-studio-mobile",
    "update-popup-persistence",
    "earbud-disconnect",
    "earbud-reconnection",
    "device-settings",
    "firmware-update"
  ],
  "source_last_updated": "1763382835",
  "source_hash": "35b458874d5a066cc82004a5da98b5ee5bada6c2e459b81b4ed28ffd7f39666e",
  "context_version": "v1",
  "processed_at": "2026-04-25T09:32:26.236157Z",
  "status": "active"
}