{
  "id": "66363516",
  "source": "testrail",
  "type": "testcase",
  "project": "411453",
  "title": "[Cloud] Flamingo - Pair headset with charge case",
  "feature": "Cloud - Device Pairing",
  "scenario": "Verify that a Flamingo headset paired with the app and logged into an account is properly displayed on the Cloud website with separate earpiece and charge case entries when paired with the charge case.",
  "steps": [
    "Turn off the Flamingo headset",
    "Place the headset in the charge case",
    "Close the charge case",
    "Open the charge case",
    "Turn on the headset"
  ],
  "expected": "Headset turns on. The app shows battery levels for both the headset and the charge case. The Cloud web page displays the device as \"Voyager Legend 50 UC\". The device details page shows separate entries for the earpiece and charge case with images and component sections.",
  "coverage": [],
  "edge_cases": [],
  "keywords": [
    "Flamingo headset",
    "charge case",
    "Cloud website",
    "earpiece entries",
    "pairing",
    "app account",
    "device display",
    "Bluetooth pairing"
  ],
  "source_last_updated": "1762331223",
  "source_hash": "d232ced6fe22a87b07530dd4a1b8aedf0902b4633d41a5c1a93c019db2c5e237",
  "context_version": "v1",
  "processed_at": "2026-04-24T11:50:53.344816Z",
  "status": "active"
}